{"PREVALENCE_BY_GENDER_AGE_YEAR":{"TRELLIS_NAME":[],"SERIES_NAME":[],"X_CALENDAR_YEAR":[],"Y_PREVALENCE_1000PP":[]},"PREVALENCE_BY_MONTH":{"X_CALENDAR_MONTH":[],"Y_PREVALENCE_1000PP":[]},"CONDITIONS_BY_TYPE":{"CONCEPT_NAME":["Claim- Inpatient: Secondary diagnosis","EHR Chief Complaint"],"COUNT_VALUE":[504,10]},"AGE_AT_FIRST_DIAGNOSIS":{"CATEGORY":["MALE","FEMALE"],"MIN_VALUE":[23,20],"P10_VALUE":[35,29],"P25_VALUE":[45,40],"MEDIAN_VALUE":[56,53],"P75_VALUE":[68,68],"P90_VALUE":[73,77],"MAX_VALUE":[300,300]}}
