{"PREVALENCE_BY_GENDER_AGE_YEAR":{"TRELLIS_NAME":"50-59","SERIES_NAME":"MALE","X_CALENDAR_YEAR":2192,"Y_PREVALENCE_1000PP":109.09091},"PREVALENCE_BY_MONTH":{"X_CALENDAR_MONTH":[],"Y_PREVALENCE_1000PP":[]},"CONDITIONS_BY_TYPE":{"CONCEPT_NAME":["Claim- Inpatient: Primary diagnosis","Claim- Inpatient: Secondary diagnosis"],"COUNT_VALUE":[32,945]},"AGE_AT_FIRST_DIAGNOSIS":{"CATEGORY":["FEMALE","MALE"],"MIN_VALUE":[15,17],"P10_VALUE":[22,22],"P25_VALUE":[33,31],"MEDIAN_VALUE":[45,46],"P75_VALUE":[58,58],"P90_VALUE":[69,70],"MAX_VALUE":[88,300]}}
