{"PREVALENCE_BY_GENDER_AGE_YEAR":{"TRELLIS_NAME":"50-59","SERIES_NAME":"MALE","X_CALENDAR_YEAR":2145,"Y_PREVALENCE_1000PP":107.14286},"PREVALENCE_BY_MONTH":{"X_CALENDAR_MONTH":[],"Y_PREVALENCE_1000PP":[]},"PROCEDURE_FREQUENCY_DISTRIBUTION":{"Y_NUM_PERSONS":[1,1,1,0,0,0,0,0,0,0,0,0,0,0],"X_COUNT":[1,2,3,4,5,6,7,8,9,10,11,12,13,14]},"PROCEDURES_BY_TYPE":{"CONCEPT_NAME":"EHR order list entry","COUNT_VALUE":2003},"AGE_AT_FIRST_OCCURRENCE":{"CATEGORY":["FEMALE","MALE"],"MIN_VALUE":[21,17],"P10_VALUE":[43,43],"P25_VALUE":[53,52],"MEDIAN_VALUE":[65,64],"P75_VALUE":[75,74],"P90_VALUE":[82,82],"MAX_VALUE":[308,302]}}
